<ui:UiBinder xmlns:ui='urn:ui:com.google.gwt.uibinder'
    xmlns:g='urn:import:com.google.gwt.user.client.ui'
    xmlns:my='urn:import:es.deusto.weblab.client.ui.themes.es.deusto.weblab.defaultweb.widgets'
    xmlns:w="urn:import:es.deusto.weblab.client.ui.widgets">
    
    <ui:with field='res' type='es.deusto.weblab.client.ui.themes.es.deusto.weblab.defaultweb.Resources'/>
        
    <g:VerticalPanel ui:field="containerPanel" styleName="web-login-container">
    
    	<g:VerticalPanel styleName="web-login-box">
    
	    	<g:HorizontalPanel styleName="web-login-logo">
		   		<g:Image resource='{res.logo}' />
			</g:HorizontalPanel>
			
	   		<g:HorizontalPanel ui:field="langsPanel" styleName="web-login-languages" />		    	
	    	
	    	<g:VerticalPanel styleName="web-login-form">
	    	
		    	<my:EasyGrid ui:field="grid" cols='2' rows='2' styleName="web-login-form-fields">
		    	
					<g:Label ui:field="usernameLabel"></g:Label>
					<g:TextBox ui:field="usernameTextbox"></g:TextBox>
					
					<g:Label ui:field="passwordLabel"></g:Label>
					<g:PasswordTextBox ui:field="passwordTextbox"></g:PasswordTextBox>
		    	
		    	</my:EasyGrid>			    	
			    	
			    <g:HorizontalPanel styleName="web-login-form-button">
					<g:Button ui:field="loginButton">Log in</g:Button>
				</g:HorizontalPanel>
	
			</g:VerticalPanel>
			
			<w:WlWaitingLabel ui:field="waitingLabel" styleName="web-waiting-label"></w:WlWaitingLabel>
			<g:Label ui:field="generalErrorLabel" styleName="web-error-message"></g:Label>
		
		</g:VerticalPanel>
	
		<g:HorizontalPanel styleName="web-login-foot-message">
			<g:HTML ui:field="demoAvailableHTML"></g:HTML>	
		</g:HorizontalPanel>
		
		<g:HorizontalPanel styleName="web-login-foot-message">
			<g:HTML ui:field="supportHTML"></g:HTML>
		</g:HorizontalPanel>
				
	</g:VerticalPanel>
	
</ui:UiBinder>